{
    "exported_at": "2026-01-31T23:03:40.308186",
    "count": 21,
    "items": [
        {
            "category": "Card",
            "sub_category": "Pokemon",
            "name": "2005 Pok\u00e9mon Japanese Play Espeon",
            "description": "Graded - PSA 10: Mint condition! Holo Promo 50,000pts",
            "owner": "PWCC Auctions",
            "status": null,
            "history": null,
            "price": 48000,
            "url_for_pic": "https://cdn.shopify.com/s/files/1/0126/7843/0777/files/2005_Pokemon_Japanese_Play_Promo_40_000_Pts._Holo_Espeon_Gold_Star_1024x1024.jpg?v=1708355398",
            "valid": true
        },
        {
            "category": "Card",
            "sub_category": "Pokemon",
            "name": "1999 Charizard CGC 10",
            "description": "Iconic Vintage 1st Edition Charizard. Mint condition!",
            "owner": "RarePokeVault",
            "status": null,
            "history": null,
            "price": 400000,
            "url_for_pic": "https://i.ebayimg.com/images/g/cYoAAOSwxLNmGXKW/s-l1600.png       |.    https://i.ebayimg.com/images/g/iXwAAOSw7S5mGXKA/s-l1600.png",
            "valid": true
        },
        {
            "category": "Card",
            "sub_category": "Pokemon",
            "name": "2005 POKEMON JAPANESE PROMO VICTORY ORB",
            "description": "Graded - PSA 10: Mint condition! HOLO SUMMER BATTLE ROAD",
            "owner": "PWCC Auctions",
            "status": null,
            "history": null,
            "price": 60000,
            "url_for_pic": "https://cdn.shopify.com/s/files/1/0126/7843/0777/files/2005_POKEMON_JAPANESE_SUMMER_BATTLE_ROAD_MEW_VICTORY_ORB_TROPHY_1024x1024.jpg?v=1708355785",
            "valid": true
        },
        {
            "category": "Card",
            "sub_category": "Yu-Gi-Oh",
            "name": "2002 Yu-Gi-Oh! Gaia the Fierce Knight #006 1st Edition",
            "description": "Graded - PSA 10: Professionally graded Legend of Blue Eyes White Dragon",
            "owner": "Heritage Auctions",
            "status": null,
            "history": null,
            "price": 4560,
            "url_for_pic": "https://cdn.shopify.com/s/files/1/0126/7843/0777/files/YGOC_23_1024x1024.jpg?v=1740169828",
            "valid": true
        },
        {
            "category": "Card",
            "sub_category": "Yu-Gi-Oh",
            "name": "2005 Yu-Gi-Oh! Des Volstgalph EN002",
            "description": "Pharaoh Tour Promo",
            "owner": "Heritage Auctions",
            "status": null,
            "history": null,
            "price": 6000,
            "url_for_pic": "https://cdn.shopify.com/s/files/1/0126/7843/0777/files/YGOC_27_1024x1024.jpg?v=1740169828",
            "valid": true
        },
        {
            "category": "Card",
            "sub_category": "Yu-Gi-Oh",
            "name": "2002 Yu-Gi-Oh! Exodia the Forbidden One #124 1st Edition",
            "description": "Legend of Blue Eyes White Dragon",
            "owner": "Heritage Auctions",
            "status": null,
            "history": null,
            "price": 4560,
            "url_for_pic": "https://cdn.shopify.com/s/files/1/0126/7843/0777/files/YGOC_21_1024x1024.jpg?v=1740169828",
            "valid": true
        },
        {
            "category": "Card",
            "sub_category": "MTG",
            "name": "Magic: The Gathering Mox Pearl Gamma Playtest",
            "description": "CGC 8: Professionally graded",
            "owner": "Heritage Auctions",
            "status": null,
            "history": null,
            "price": 13750,
            "url_for_pic": "https://cdn.shopify.com/s/files/1/0126/7843/0777/files/MTG_30_7e676c8f-4299-40f3-8e5e-687c8bb49485_1024x1024.jpg?v=1746035690",
            "valid": true
        },
        {
            "category": "Card",
            "sub_category": "MTG",
            "name": "1993 Magic: The Gathering Alpha Mox Ruby",
            "description": "PSA 10: Professionally graded",
            "owner": "Fanatics Collect",
            "status": null,
            "history": null,
            "price": 39600,
            "url_for_pic": "https://cdn.shopify.com/s/files/1/0126/7843/0777/files/MTG_13_b4f93f61-3ea5-4253-818d-ad019553c3a8_1024x1024.jpg?v=1746035691",
            "valid": true
        },
        {
            "category": "Card",
            "sub_category": "MTG",
            "name": "1997 Magic: The Gathering Splendid Genesis",
            "description": "BGS 8 : Richard Garfield Promo #RG97",
            "owner": "Heritage Auctions",
            "status": null,
            "history": null,
            "price": 72000,
            "url_for_pic": "https://cdn.shopify.com/s/files/1/0126/7843/0777/files/MTG_6_e5030ce7-bdd2-4480-8c63-3579b16a4ed0_1024x1024.jpg?v=1746035691",
            "valid": true
        },
        {
            "category": "Game Items",
            "sub_category": "Console",
            "name": "Nintendo 64 N64 Launch Edition Console",
            "description": "New in Box: Ultra Rare",
            "owner": "skillit23",
            "status": null,
            "history": null,
            "price": 75000,
            "url_for_pic": "https://i.ebayimg.com/images/g/ITIAAOSwKophWy8e/s-l1600.webp",
            "valid": true
        },
        {
            "category": "Game Items",
            "sub_category": "Console",
            "name": "Atari CX-2600A Video Computer System Game Console",
            "description": "NEW Factory Sealed RARE",
            "owner": "orlylicensedproduct",
            "status": null,
            "history": null,
            "price": 10000,
            "url_for_pic": "https://i.ebayimg.com/images/g/KU4AAOSwbqRl2Kqd/s-l1600.webp",
            "valid": true
        },
        {
            "category": "Game Items",
            "sub_category": "Console",
            "name": "PLAYSTATION 1 SCPH-1000 JAPAN RELEASE 1994",
            "description": "NEW Factory Sealed Ultra RARE",
            "owner": "manticore84",
            "status": null,
            "history": null,
            "price": 12499,
            "url_for_pic": "https://i.ebayimg.com/images/g/qfcAAOSwykFm7JGH/s-l1600.webp",
            "valid": true
        },
        {
            "category": "Game Items",
            "sub_category": "Cartridge",
            "name": "1990 NINTENDO WORLD CHAMPIONSHIPS NES CARTRIDGE GREY WATA 6.5",
            "description": "Professionally Graded and in good condition",
            "owner": "OTIA Rips",
            "status": null,
            "history": null,
            "price": 175000,
            "url_for_pic": "https://i.ebayimg.com/images/g/TAUAAOSw6-9iau-R/s-l1600.webp",
            "valid": true
        },
        {
            "category": "Game Items",
            "sub_category": "Cartridge",
            "name": "Nintendo World Championships: NES Edition Switch Cartridge",
            "description": "Graded CGC 10: Mint condition",
            "owner": "cyan9-93",
            "status": null,
            "history": null,
            "price": 250,
            "url_for_pic": "https://i.ebayimg.com/images/g/YCkAAeSw9dlpQziz/s-l1600.webp",
            "valid": true
        },
        {
            "category": "Game Items",
            "sub_category": "Cartridge",
            "name": "New Open Box Super Mario Bros. 3 NES Challenge Set",
            "description": "(RARE)Not For Resale Edition: Mint condition",
            "owner": "flevre",
            "status": null,
            "history": null,
            "price": 750,
            "url_for_pic": "https://i.ebayimg.com/images/g/-M8AAeSw-4hpYHyT/s-l1600.webp",
            "valid": true
        },
        {
            "category": "Game Items",
            "sub_category": "Merch",
            "name": "Fallout Pip-Boy 3000 Prop replica",
            "description": "The first ever fully functional, supremely accurate, wearable 1:1 replica of the Pip-Boy 3000 as used in Fallout 3 and Fallout New Vegas, with working FM radio and alarm clock. Created by The Wand Company using the game geometry with extra details from the original high-poly model created by the game designers, this gorgeous replica has a functioning in-plane switching (IPS) LCD screen showing almost all of the in-game content. It is also a working timepiece with an alarm clock function \u2013 ideal for when it is sitting neatly on its perfectly-formed display stand. Not only fully functional, but wearable, and exhibition-grade displayable, this has to be the ultimate replica.",
            "owner": "GameStop",
            "status": null,
            "history": null,
            "price": 300,
            "url_for_pic": "https://encrypted-tbn0.gstatic.com/shopping?q=tbn:ANd9GcQIWm95Xv7IJO8bbKzjZJMP4ujoHkW-YkBTA49ig2FmUUChnkg6YVG6paQ5vldr-Ea_MF4QCMrGbO7lANMc4FYhJXvCiEdNyM1SqESkFWA2VLhnH60uaOqv",
            "valid": true
        },
        {
            "category": "Game Items",
            "sub_category": "Merch",
            "name": null,
            "description": null,
            "owner": null,
            "status": null,
            "history": null,
            "price": null,
            "url_for_pic": null,
            "valid": false,
            "errors": [
                "name"
            ]
        },
        {
            "category": "Game Items",
            "sub_category": "Merch",
            "name": null,
            "description": null,
            "owner": null,
            "status": null,
            "history": null,
            "price": null,
            "url_for_pic": null,
            "valid": false,
            "errors": [
                "name"
            ]
        },
        {
            "category": "Wardrobe",
            "sub_category": "Vintage",
            "name": "AC/DC - Highway to Hell Signed Limited Edition Mini Poster",
            "description": "AC/DC \u2018Highway to Hell\u2019 Mini Poster \u2013 Exclusive Hand-Signed. 1 of 100",
            "owner": null,
            "status": null,
            "history": null,
            "price": 250,
            "url_for_pic": "https://store.rare-t.com/_next/image?url=https%3A%2F%2Fmedias.rare-t.com%2Facdc-highway-to-hell-mini-frame-1.jpg&w=1920&q=75",
            "valid": true
        },
        {
            "category": "Wardrobe",
            "sub_category": "Vintage",
            "name": "Vintage 80's Military Duffle Bag",
            "description": "Authentic Flyer's Aviator Duffle Bag. Good condition",
            "owner": "TheOneStitch",
            "status": null,
            "history": null,
            "price": 35,
            "url_for_pic": "https://lh3.google.com/gg-dl/AOI_d__ft9DR6tZKYreAipeG87-cLcXSkh3B1WeominaTZzXtc6wUGFr5kwz2gM0Ju9mO5IP2GPJ2fUwqSrPEQJ3lXTtKppeVgfO7yqt6BPXYAPtjUrjf0mjBZsnm-XpvOVar72TRC4aU_QW_8Uvfr7X4x8yb67IeaVI6Vjh69pHP-cVvFbQ=s1024-rj",
            "valid": true
        },
        {
            "category": "Wardrobe",
            "sub_category": "Vintage",
            "name": null,
            "description": null,
            "owner": null,
            "status": null,
            "history": null,
            "price": null,
            "url_for_pic": null,
            "valid": false,
            "errors": [
                "name"
            ]
        }
    ]
}